passme/__init__.py
passme/calc.py
passme/html.py
passme/main.py
passme-1.2.4.dist-info/licenses/LICENSE.txt
passme-1.2.4.dist-info/METADATA
passme-1.2.4.dist-info/WHEEL
passme-1.2.4.dist-info/entry_points.txt
passme-1.2.4.dist-info/top_level.txt
passme-1.2.4.dist-info/RECORD
